pecowaco/GaussFit.py
pecowaco/Normalize.py
pecowaco/Strip2DFFT.py
pecowaco/__init__.py
pecowaco/plot_utils.py
pecowaco-1.0.1.dist-info/LICENSE
pecowaco-1.0.1.dist-info/METADATA
pecowaco-1.0.1.dist-info/WHEEL
pecowaco-1.0.1.dist-info/entry_points.txt
pecowaco-1.0.1.dist-info/top_level.txt
pecowaco-1.0.1.dist-info/RECORD
