Metadata-Version: 2.1
Name: pecowaco
Version: 1.0.1
Summary: Analysis of Periodic contractions
Home-page: https://github.com/MechaBlasto/PeCoWaCo/
Author: Varun Kapoor,OOzge Ozguc
Author-email: randomaccessiblekapoor@gmail.com
License: UNKNOWN
Platform: UNKNOWN
Classifier: Development Status :: 3 - Alpha
Classifier: Natural Language :: English
Classifier: License :: OSI Approved :: MIT License
Classifier: Operating System :: OS Independent
Classifier: Programming Language :: Python
Classifier: Programming Language :: Python :: 3.7
License-File: LICENSE
Requires-Dist: numpy
Requires-Dist: pandas
Requires-Dist: napari
Requires-Dist: bokeh
Requires-Dist: scikit-image
Requires-Dist: scipy
Requires-Dist: tifffile
Requires-Dist: matplotlib
